[
  { "nombre": "Miguel Ángel Vargas", "cargo": "Gerencia TI", "email": "miguel.angel.vargas@unifrutti.com", "foto": "/team/migue.png" },
  { "nombre": "Erick Olguín Osorio", "cargo": "Sub-Gerente de Soporte y Seguridad Informática", "email": "erick.olguin@unifrutti.com", "foto": "/team/erick.png" },
  { "nombre": "Claudio Vasquez", "cargo": "Sub-Gerente de Desarrollo e Innovación", "email": "claudio.vasquez@unifrutti.com", "foto": "/team/claudio.png" },
  { "nombre": "Juan Gabriel Gonzales Cruz", "cargo": "Sub Gerencia TI, Perú", "email": "gabriel.gonzales@unifrutti.com", "foto": "/team/team_5_4.png" },
  { "nombre": "Ricardo Alvarado", "cargo": "Jefe de Soporte y Ciberseguridad", "email": "ricardo.alvarado@unifrutti.com", "foto": "/team/ricardo.png" },
  { "nombre": "Benjamín Lopez", "cargo": "Arquitecto de Datos y Líder Técnico Desarrollo", "email": "benjamin.lopez@unifrutti.com", "foto": "/team/benjy.png" },
  { "nombre": "Felipe Henríquez", "cargo": "Encargado de Infraestructura TI", "email": "felipe.henriquez@unifrutti.com", "foto": "/team/felipe.png" },
  { "nombre": "Orlando Tobar", "cargo": "Encargado de Mesa de Ayuda y Monitoreo", "email": "orlando.tobar@unifrutti.com", "foto": "/team/orlando.png" },
  { "nombre": "Isaac Vilchez", "cargo": "Soporte y Redes TI", "email": "isaac.vilchez@unifrutti.com", "foto": "/team/isa.png" },
  { "nombre": "Mario Garrido", "cargo": "Soporte y Redes TI", "email": "mario.garrido@unifrutti.com", "foto": "/team/mario.png" },
  { "nombre": "David Portocarrero", "cargo": "Programador de Sistemas", "email": "david.portocarrero@unifrutti.com", "foto": "/team/david.png" },
  { "nombre": "Jorge Toledo", "cargo": "Líder de Proyecto Desarrollo Web", "email": "jorge.toledo@unifrutti.com", "foto": "/team/jorge.png" },
  { "nombre": "Elías Guere", "cargo": "Análisis de Gestión", "email": "elias.guere@unifrutti.com", "foto": "/team/elias-guere.png" },
  { "nombre": "Jean Carlos Alban", "cargo": "Coordinador de Desarrollo e Implementación Tec.", "email": "jeancarlos.alban@unifrutti.com", "foto": "/team/jean-carlos.png" },
  { "nombre": "Jorge Sazo", "cargo": "Desarrollador Multimedia Frontend", "email": "jorge.sazo@unifrutti.com", "foto": "/team/sazo.png" },
  { "nombre": "Miguel Ancajima", "cargo": "Desarrollador Full Stack (Móvil)", "email": "miguel.ancajima@unifrutti.com", "foto": "/team/miguel-alcajima.png" },
  { "nombre": "Anthony Guzmán", "cargo": "Supervisor de redes e infraestructura", "email": "anthony.guzman@unifrutti.com", "foto": "/team/antonhy.png" },
  { "nombre": "Luis Nima", "cargo": "Encargado de Soporte de TI", "email": "luis.nima@unifrutti.com", "foto": "/team/luis-nima.png" },
  { "nombre": "Jimmy Sernaque", "cargo": "Asistente de Redes e Infraestructura TI", "email": "jimmy.sernaque@unifrutti.com", "foto": "/team/jimmy.png" },
  { "nombre": "Marcos Gonzáles", "cargo": "Asistente de Soporte TI", "email": "marcos.gonzales@unifrutti.com", "foto": "/team/marco.png" }
]
