{
  "id": "frio-packing-presion-de-etiquetas-desde-proceso-de-packing",
  "title": "~$presión de etiquetas desde Proceso de Packing",
  "sourcePath": "/Users/desarrolloverfrut/Documents/Manuales/Frio Packing/~$presión de etiquetas desde Proceso de Packing.docx",
  "relativePath": "Frio Packing/~$presión de etiquetas desde Proceso de Packing.docx",
  "sourceFolder": "Frio Packing",
  "system": "ERP",
  "module": "Frio Packing",
  "extension": "docx",
  "sizeBytes": 162,
  "modifiedAt": "2021-09-22T21:35:37.417Z",
  "status": "pendiente_revision",
  "notes": "",
  "extractedAt": "2026-07-02T19:09:08.971Z",
  "extraction": {
    "status": "extracted",
    "method": "textutil",
    "warnings": []
  },
  "textLength": 162,
  "text": "\u0000\u0000\u0000\u0000\u0000\u0000\u0000\u0000\u0000\u0000\u0000\u0000\u0000\u0000\u0000\u0000\u0000\u0000\u0000\u0000\u0000\u0000\u0000\u0000\u0000\u0000\u0000\u0000\u0000\u0000\u0000\u0000\u0000\u0000\u0000\u0000\u0000\u0000\u0000\u0000\u0000\u0000\u0000\u0000\u0000\u0000\u0000\u0000\u0000\u0000\u0000\u0000\u0000\u0000\u0000\u0000\u0000\u0000\u0000\u0000\u0000\u0000\nB÷C\u0000\u0006\u0000å\u0000\u0000\u0000\u0000\u0000\u0000\u0000\u0000\fB◊C\u0000\u0007\u0000ãWord\u0000\u0000\u0000\u0000\u000fB–C\u0000\b\u0000åáˇˇ\u0003\u0000\u0000\u0000\u0000\u000eB—C\u0000\t\u0000é \u0000\u0000\u0000\u0000\u0000\u0000\u0000\u0011B“C\u0000\n\u0000å\n\f\u0000\u0000\u0000\u0000\u0000\u0000\u0010B”C\u0000\u000b\u0000àÄÕ≤∏∏\u0001\u0000\u0000\u0013BÃC"
}
